Metadata-Version: 1.0
Name: rrbayesnet
Version: 0.0.2
Summary: Python bayesian network implementation.
Home-page: https://github.com/robertriosm/lab-2-ia
Author: Roberto Rios
Author-email: rio20979@uvg.edu.gt
License: MIT
Platform: UNKNOWN
